nonebot_plugin_mcpclient/__init__.py
nonebot_plugin_mcpclient/client.py
nonebot_plugin_mcpclient/commands.py
nonebot_plugin_mcpclient/config.py
nonebot_plugin_mcpclient/permission.py
nonebot_plugin_mcpclient-0.1.2.dist-info/METADATA
nonebot_plugin_mcpclient-0.1.2.dist-info/WHEEL
nonebot_plugin_mcpclient-0.1.2.dist-info/licenses/LICENSE
nonebot_plugin_mcpclient-0.1.2.dist-info/RECORD
