Metadata-Version: 2.4
Name: nonebot-plugin-mcpclient
Version: 0.1.2
Summary: NoneBot2 MCP Client Plugin - 提供 MCP 工具调用能力
Author-email: gsskk <your.email@example.com>
License: MIT License
License-File: LICENSE
Requires-Python: >=3.10
Requires-Dist: anyio>=4.0.0
Requires-Dist: mcp>=1.0.0
Requires-Dist: nonebot-plugin-alconna>=0.50.2
Requires-Dist: nonebot2>=2.3.0
Provides-Extra: dev
Requires-Dist: pytest-asyncio>=0.21.0; extra == 'dev'
Requires-Dist: pytest>=7.0.0; extra == 'dev'
Requires-Dist: ruff>=0.1.0; extra == 'dev'
